chess_battle_advanced/__init__.py
chess_battle_advanced/cba.png
chess_battle_advanced/chessbattleadvanced.mp4
chess_battle_advanced-1.1.3.dist-info/LICENSE
chess_battle_advanced-1.1.3.dist-info/METADATA
chess_battle_advanced-1.1.3.dist-info/WHEEL
chess_battle_advanced-1.1.3.dist-info/entry_points.txt
chess_battle_advanced-1.1.3.dist-info/top_level.txt
chess_battle_advanced-1.1.3.dist-info/RECORD
